qtwidgets/__init__.py
qtwidgets/dock_widget.py
qtwidgets/observablelist.py
qtwidgets/utils.py
qtwidgets/browser/__init__.py
qtwidgets/browser/browser_config.py
qtwidgets/browser/browser_widget.py
qtwidgets/browser/page_layout.py
qtwidgets/browser/tool_bar_manager.py
qtwidgets/console/__init__.py
qtwidgets/console/console_config.py
qtwidgets/console/console_widget.py
qtwidgets/gallery/__init__.py
qtwidgets/gallery/gallery_widget.py
qtwidgets/gallery/image_button.py
qtwidgets/worker/__init__.py
qtwidgets/worker/worker.py
qtwidgets/worker/worker_manager_widget.py
qtwidgets/worker/worker_status.py
qtwidgets/worker/worker_widget.py
qt_widgets-0.0.1.dev7.dist-info/LICENSE
qt_widgets-0.0.1.dev7.dist-info/METADATA
qt_widgets-0.0.1.dev7.dist-info/WHEEL
qt_widgets-0.0.1.dev7.dist-info/top_level.txt
qt_widgets-0.0.1.dev7.dist-info/RECORD
