Metadata-Version: 2.1
Name: qt-widgets
Version: 0.0.1.dev7
Summary: Qt widgets library
Home-page: https://github.com/flegac/qt-widgets
Author: flegac
License: UNKNOWN
Project-URL: Bug Tracker, https://github.com/flegac/qt-widgets/issues
Platform: UNKNOWN
Classifier: Programming Language :: Python :: 3
Classifier: License :: OSI Approved :: MIT License
Classifier: Operating System :: OS Independent
Requires-Python: >=3.7
License-File: LICENSE
Requires-Dist: pyqt5
Requires-Dist: pyqt5-tools
Requires-Dist: qimage2ndarray
